[
{
  "model": "polls.poll",
  "pk": 1,
  "fields": {
    "name": "Poll 1",
    "creator": 3,
    "allow": 2,
    "res": 0,
    "image": "https://external-content.duckduckgo.com/iu/?u=https%3A%2F%2Fwww.publicdomainpictures.net%2Fpictures%2F170000%2Fvelka%2Fsuperman.jpg&f=1&nofb=1&ipt=a2fc3be8cd1d24aedb1aac3181302ecc71e30ae0ebd215e79a76e7da799147d1&ipo=images",
    "yaml": "name: \"Poll 1\"\nimage: \"https://external-content.duckduckgo.com/iu/?u=https%3A%2F%2Fwww.publicdomainpictures.net%2Fpictures%2F170000%2Fvelka%2Fsuperman.jpg&f=1&nofb=1&ipt=a2fc3be8cd1d24aedb1aac3181302ecc71e30ae0ebd215e79a76e7da799147d1&ipo=images\"\nallow: AUTH\nres: '*'\npoll:\n    - info:\n        type: LABEL\n        text: \"Example poll 1\"\n        label: \"The purpose of this poll is to know what superpower people want and\\n what they like to do on weekends.\"\n    - superpower:\n        required: true\n        type: CHOICE\n        text: \"Which superpower would you rather have?\"\n        choices:\n            - invis: \"Invisibility\"\n            - tp: \"Teleportation\"\n            - speed: \"Super speed\"\n            - time: \"Time manipulation\"\n    - weekend:\n        required: true\n        type: CHOICE\n        text: \"What's your favorite way to spend a weekend?\"\n        choices:\n            - tv: \"Binge-watching TV shows\"\n            - outdoors: \"Exploring the great outdoors\"\n            - camp: \"Camping\"\n            - game: \"Gaming\"",
    "pub_date": "2024-09-03T19:25:46Z",
    "end_date": null
  }
},
{
  "model": "polls.poll",
  "pk": 2,
  "fields": {
    "name": "Poll 2",
    "creator": 3,
    "allow": 2,
    "res": 0,
    "image": "https://external-content.duckduckgo.com/iu/?u=https%3A%2F%2Fwww.publicdomainpictures.net%2Fpictures%2F280000%2Fvelka%2Fgolden-dragon-1543960150tr0.jpg&f=1&nofb=1&ipt=8d469af2d301eb2fff7f77bf68fe658c75df6347377e03cdbd2c4f30a6d7d5fa&ipo=images",
    "yaml": "name: \"Poll 2\"\nimage: \"https://external-content.duckduckgo.com/iu/?u=https%3A%2F%2Fwww.publicdomainpictures.net%2Fpictures%2F280000%2Fvelka%2Fgolden-dragon-1543960150tr0.jpg&f=1&nofb=1&ipt=8d469af2d301eb2fff7f77bf68fe658c75df6347377e03cdbd2c4f30a6d7d5fa&ipo=images\"\nallow: AUTH\nres: '*'\npoll:\n    - info:\n        type: LABEL\n        text: \"Example poll 2\"\n        label: \"The purpose of this poll is to know whather people prefer to go to the past or the future and\\n what mode of transportation they like.\"\n    - time:\n        required: true\n        type: CHOICE\n        text: \"If you could time travel, where would you go?\"\n        choices:\n            - past: \"Past\"\n            - cur: \"I won't time travel.\"\n            - fut: \"Future\"\n    - transpt:\n        required: true\n        type: CHOICE\n        text: \"Pick a mode of transportation\"\n        choices:\n            - dragon: \"Flying on a dragon\"\n            - pirateship: \"Sailing the seas on a pirate ship\"\n            - car: \"Car\"\n            - bus: \"The flying bus from Fortnite\"",
    "pub_date": "2024-09-03T19:26:16Z",
    "end_date": null
  }
},
{
  "model": "polls.poll",
  "pk": 3,
  "fields": {
    "name": "Closed Poll",
    "creator": 3,
    "allow": 2,
    "res": 0,
    "image": "https://external-content.duckduckgo.com/iu/?u=https%3A%2F%2Fupload.wikimedia.org%2Fwikipedia%2Ffr%2Fe%2Fe3%2FTime_Machine_logo.png%3F20090706183129&f=1&nofb=1&ipt=03cf14394a2bf711594df8e1be8cdaddec2724b048795779eb461b17bf1d5078&ipo=images",
    "yaml": "name: \"Closed Poll\"\nimage: \"https://external-content.duckduckgo.com/iu/?u=https%3A%2F%2Fupload.wikimedia.org%2Fwikipedia%2Ffr%2Fe%2Fe3%2FTime_Machine_logo.png%3F20090706183129&f=1&nofb=1&ipt=03cf14394a2bf711594df8e1be8cdaddec2724b048795779eb461b17bf1d5078&ipo=images\"\nallow: AUTH\nres: '*'\nbegin: 1\nend: 1\npoll:\n    - info:\n        type: LABEL\n        text: \"Example poll 2\"\n        label: \"The purpose of this poll is to know whather people prefer to go to the past or the future and\\n what mode of transportation they like.\"\n    - time:\n        required: true\n        type: CHOICE\n        text: \"If you could time travel, where would you go?\"\n        choices:\n            - past: \"Past\"\n            - cur: \"I won't time travel.\"\n            - fut: \"Future\"",
    "pub_date": "1969-12-31T17:00:01Z",
    "end_date": "1969-12-31T17:00:01Z"
  }
},
{
  "model": "polls.poll",
  "pk": 4,
  "fields": {
    "name": "Poll open in 2025",
    "creator": 3,
    "allow": 2,
    "res": 0,
    "image": "https://external-content.duckduckgo.com/iu/?u=https%3A%2F%2Fupload.wikimedia.org%2Fwikipedia%2Ffr%2Fe%2Fe3%2FTime_Machine_logo.png%3F20090706183129&f=1&nofb=1&ipt=03cf14394a2bf711594df8e1be8cdaddec2724b048795779eb461b17bf1d5078&ipo=images",
    "yaml": "name: \"Poll open in 2025\"\nimage: \"https://external-content.duckduckgo.com/iu/?u=https%3A%2F%2Fupload.wikimedia.org%2Fwikipedia%2Ffr%2Fe%2Fe3%2FTime_Machine_logo.png%3F20090706183129&f=1&nofb=1&ipt=03cf14394a2bf711594df8e1be8cdaddec2724b048795779eb461b17bf1d5078&ipo=images\"\nallow: AUTH\nres: '*'\nbegin: 1735693200\npoll:\n    - info:\n        type: LABEL\n        text: \"Example poll 2\"\n        label: \"The purpose of this poll is to know whather people prefer to go to the past or the future and\\n what mode of transportation they like.\"\n    - time:\n        required: true\n        type: CHOICE\n        text: \"If you could time travel, where would you go?\"\n        choices:\n            - past: \"Past\"\n            - cur: \"I won't time travel.\"\n            - fut: \"Future\"",
    "pub_date": "2024-12-31T18:00:00Z",
    "end_date": null
  }
}
]
